adjutant/__init__.py
adjutant/core.py
adjutant/exceptions.py
adjutant/feature_set.py
adjutant/middleware.py
adjutant/settings.py
adjutant/urls.py
adjutant/version.py
adjutant/wsgi.py
adjutant/actions/__init__.py
adjutant/actions/models.py
adjutant/actions/utils.py
adjutant/actions/migrations/0001_initial.py
adjutant/actions/migrations/0002_action_auto_approve.py
adjutant/actions/migrations/0003_auto_20190610_0205.py
adjutant/actions/migrations/0004_auto_20190610_0209.py
adjutant/actions/migrations/0005_alter_action_auto_approve.py
adjutant/actions/migrations/__init__.py
adjutant/actions/v1/__init__.py
adjutant/actions/v1/base.py
adjutant/actions/v1/misc.py
adjutant/actions/v1/projects.py
adjutant/actions/v1/resources.py
adjutant/actions/v1/serializers.py
adjutant/actions/v1/users.py
adjutant/actions/v1/tests/__init__.py
adjutant/actions/v1/tests/test_misc_actions.py
adjutant/actions/v1/tests/test_project_actions.py
adjutant/actions/v1/tests/test_resource_actions.py
adjutant/actions/v1/tests/test_user_actions.py
adjutant/api/__init__.py
adjutant/api/exception_handler.py
adjutant/api/models.py
adjutant/api/urls.py
adjutant/api/utils.py
adjutant/api/views.py
adjutant/api/migrations/0001_initial.py
adjutant/api/migrations/0002_auto_20160815_2249.py
adjutant/api/migrations/0003_task_approved_by.py
adjutant/api/migrations/0004_auto_20160929_0317.py
adjutant/api/migrations/0005_auto_20190610_0209.py
adjutant/api/migrations/0006_auto_20190610_0209.py
adjutant/api/migrations/0007_auto_20190610_0209.py
adjutant/api/migrations/0008_auto_20190610_0209.py
adjutant/api/migrations/__init__.py
adjutant/api/v1/__init__.py
adjutant/api/v1/base.py
adjutant/api/v1/openstack.py
adjutant/api/v1/tasks.py
adjutant/api/v1/urls.py
adjutant/api/v1/utils.py
adjutant/api/v1/views.py
adjutant/api/v1/tests/__init__.py
adjutant/api/v1/tests/test_api_admin.py
adjutant/api/v1/tests/test_api_openstack.py
adjutant/api/v1/tests/test_api_taskview.py
adjutant/commands/__init__.py
python_adjutant-11.0.0.dist-info/AUTHORS
python_adjutant-11.0.0.dist-info/LICENSE
python_adjutant-11.0.0.dist-info/METADATA
python_adjutant-11.0.0.dist-info/WHEEL
python_adjutant-11.0.0.dist-info/entry_points.txt
python_adjutant-11.0.0.dist-info/pbr.json
python_adjutant-11.0.0.dist-info/top_level.txt
python_adjutant-11.0.0.dist-info/RECORD
