Metadata-Version: 2.1
Name: python-adjutant
Version: 11.0.0
Summary: An admin task workflow service for openstack.
Home-page: https://opendev.org/openstack/adjutant
Author: OpenStack
Author-email: openstack-discuss@lists.openstack.org
License: Apache-2
Project-URL: Bug Tracker, https://storyboard.openstack.org/#!/project/openstack/adjutant
Project-URL: Documentation, https://docs.openstack.org/adjutant/latest/
Project-URL: Source Code, https://opendev.org/openstack/adjutant
Keywords: openstack,keystone,users,tasks,registration,workflow
Classifier: Development Status :: 5 - Production/Stable
Classifier: Intended Audience :: Developers
Classifier: Intended Audience :: System Administrators
Classifier: License :: OSI Approved :: Apache Software License
Classifier: Framework :: Django :: 3.2
Classifier: Programming Language :: Python :: 3
Classifier: Programming Language :: Python :: 3.9
Classifier: Programming Language :: Python :: 3.10
Classifier: Programming Language :: Python :: 3.11
Classifier: Environment :: OpenStack
License-File: LICENSE
License-File: AUTHORS
Requires-Dist: pbr >=5.2.0
Requires-Dist: Django >=4.2
Requires-Dist: Babel >=2.6.0
Requires-Dist: decorator >=4.4.0
Requires-Dist: djangorestframework >=3.14.0
Requires-Dist: jsonfield >=2.0.2
Requires-Dist: keystoneauth1 >=3.14.0
Requires-Dist: keystonemiddleware >=6.0.0
Requires-Dist: python-cinderclient >=4.1.0
Requires-Dist: python-keystoneclient >=3.19.0
Requires-Dist: python-neutronclient >=6.12.0
Requires-Dist: python-novaclient >=14.0.0
Requires-Dist: python-octaviaclient >=1.8.0
Requires-Dist: python-troveclient >=6.0.1
Requires-Dist: confspirator >=0.2.2
Requires-Dist: importlib-metadata >=6.2.1
